fluid_api_agent/__init__.py
fluid_api_agent/main.py
fluid_api_agent-0.0.8.dist-info/LICENSE
fluid_api_agent-0.0.8.dist-info/METADATA
fluid_api_agent-0.0.8.dist-info/WHEEL
fluid_api_agent-0.0.8.dist-info/RECORD
