Metadata-Version: 2.1
Name: fluid-api-agent
Version: 0.0.8
Summary: Fluid API
Home-page: https://github.com/The-Swarm-Corporation/FluidAPI
License: MIT
Keywords: artificial intelligence,deep learning,optimizers,Prompt Engineering
Author: Kye Gomez
Author-email: kye@apac.ai
Requires-Python: >=3.10,<4.0
Classifier: Development Status :: 4 - Beta
Classifier: Intended Audience :: Developers
Classifier: License :: OSI Approved :: MIT License
Classifier: Programming Language :: Python :: 3
Classifier: Programming Language :: Python :: 3.10
Classifier: Programming Language :: Python :: 3.11
Classifier: Programming Language :: Python :: 3.12
Classifier: Programming Language :: Python :: 3.9
Classifier: Topic :: Scientific/Engineering :: Artificial Intelligence
Requires-Dist: aiohttp
Requires-Dist: asyncio
Requires-Dist: loguru
Requires-Dist: pydantic
Requires-Dist: swarm-models
Requires-Dist: swarms
Requires-Dist: tenacity
Project-URL: Documentation, https://github.com/The-Swarm-Corporation/FluidAPI
Project-URL: Repository, https://github.com/The-Swarm-Corporation/FluidAPI
